plone.app.uuid-2.2.4-py3.13-nspkg.pth
plone/app/uuid/__init__.py
plone/app/uuid/browser.py
plone/app/uuid/configure.zcml
plone/app/uuid/indexer.py
plone/app/uuid/testing.py
plone/app/uuid/tests.py
plone/app/uuid/utils.py
plone_app_uuid-2.2.4.dist-info/METADATA
plone_app_uuid-2.2.4.dist-info/WHEEL
plone_app_uuid-2.2.4.dist-info/namespace_packages.txt
plone_app_uuid-2.2.4.dist-info/top_level.txt
plone_app_uuid-2.2.4.dist-info/RECORD
