Metadata-Version: 2.4
Name: plone.app.uuid
Version: 2.2.4
Summary: Plone integration for the basic plone.uuid package
Home-page: http://plone.org
Author: Martin Aspeli
Author-email: optilude@gmail.com
License: GPL
Keywords: plone uuid
Classifier: Development Status :: 5 - Production/Stable
Classifier: Framework :: Plone
Classifier: Framework :: Plone :: 6.0
Classifier: Framework :: Plone :: Core
Classifier: License :: OSI Approved :: GNU General Public License (GPL)
Classifier: Programming Language :: Python
Classifier: Programming Language :: Python :: 3.8
Classifier: Programming Language :: Python :: 3.9
Classifier: Programming Language :: Python :: 3.10
Classifier: Programming Language :: Python :: 3.11
Requires-Python: >=3.8
Requires-Dist: Products.CMFCore
Requires-Dist: Products.ZCatalog
Requires-Dist: plone.uuid
Requires-Dist: plone.indexer
Requires-Dist: setuptools
Requires-Dist: Zope
Provides-Extra: test
Requires-Dist: plone.app.testing; extra == "test"
Requires-Dist: plone.dexterity; extra == "test"
Requires-Dist: plone.testing; extra == "test"
Dynamic: author
Dynamic: author-email
Dynamic: classifier
Dynamic: description
Dynamic: home-page
Dynamic: keywords
Dynamic: license
Dynamic: provides-extra
Dynamic: requires-dist
Dynamic: requires-python
Dynamic: summary
